{
  "kind": "collectionType",
  "collectionName": "leads",
  "info": {
    "singularName": "lead",
    "pluralName": "leads",
    "displayName": "Lead"
  },
  "options": {
    "draftAndPublish": false
  },
  "pluginOptions": {},
  "attributes": {
    "email": {
      "type": "string"
    },
    "name": {
      "type": "string"
    },
    "msg": {
      "type": "richtext"
    },
    "status": {
      "type": "enumeration",
      "enum": [
        "New",
        "Spam",
        "Solved"
      ]
    }
  }
}
